.gitignore
CHANGELOG.md
MANIFEST.in
README.md
requirements.txt
setup.py
.github/workflows/main.yml
dinolemma/__init__.py
dinolemma/avocados.py
dinolemma/client.py
dinolemma/colors.py
dinolemma/dinosaurs.py
dinolemma/entity.py
dinolemma/game.py
dinolemma/gui.py
dinolemma/interactions.py
dinolemma/namer.py
dinolemma/version.py
dinolemma.egg-info/PKG-INFO
dinolemma.egg-info/SOURCES.txt
dinolemma.egg-info/dependency_links.txt
dinolemma.egg-info/entry_points.txt
dinolemma.egg-info/not-zip-safe
dinolemma.egg-info/requires.txt
dinolemma.egg-info/top_level.txt